<workflow scriptid="customworkflow_kd_new_vendor_approval">
  <description>Newly created vendor undergoes approval when Terms selected is either Due on Receipt, Net 15, Prepaid or null/empty.&#xd;
&#xd;
Approvers are either Finance Management or Ops Lead.</description>
  <initcontexts>ACTION|BANKCONNECTIVITY|BANKSTATEMENTPARSER|BUNDLEINSTALLATION|CLIENT|CSVIMPORT|CUSTOMGLLINES|CUSTOMMASSUPDATE|RECORDACTION|DATASETBUILDER|DEBUGGER|EMAILCAPTURE|FICONNECTIVITY|FIPARSER|MAPREDUCE|OFFLINECLIENT|OTHER|PAYMENTPOSTBACK|PAYMENTGATEWAY|PLATFORMEXTENSION|PORTLET|PROMOTIONS|CONSOLRATEADJUSTOR|RESTWEBSERVICES|RESTLET|ADVANCEDREVREC|SCHEDULED|SDFINSTALLATION|SHIPPINGPARTNERS|WEBSERVICES|SUITELET|TAXCALCULATION|USEREVENT|USERINTERFACE|WORKBOOKBUILDER|WORKFLOW</initcontexts>
  <initeventtypes></initeventtypes>
  <initlocalizationcontext></initlocalizationcontext>
  <initoncreate>T</initoncreate>
  <initonvieworupdate>F</initonvieworupdate>
  <initsavedsearchcondition></initsavedsearchcondition>
  <inittriggertype></inittriggertype>
  <isinactive>F</isinactive>
  <islogenabled>T</islogenabled>
  <keephistory>ALWAYS</keephistory>
  <name>Kodella | New Vendor Approval</name>
  <recordtypes>VENDOR</recordtypes>
  <releasestatus>RELEASED</releasestatus>
  <runasadmin>T</runasadmin>
  <initcondition>
    <formula></formula>
    <type>VISUAL_BUILDER</type>
  </initcondition>
  <workflowcustomfields>
    <workflowcustomfield scriptid="custworkflow_kd_created_by">
      <applyformatting>F</applyformatting>
      <defaultchecked>F</defaultchecked>
      <defaultselection></defaultselection>
      <defaultvalue></defaultvalue>
      <description></description>
      <displaytype>NORMAL</displaytype>
      <dynamicdefault></dynamicdefault>
      <fieldtype>SELECT</fieldtype>
      <help></help>
      <label>Created By (4)</label>
      <linktext></linktext>
      <maxvalue></maxvalue>
      <minvalue></minvalue>
      <selectrecordtype>-4</selectrecordtype>
      <storevalue>T</storevalue>
    </workflowcustomfield>
    <workflowcustomfield scriptid="custworkflow_kd_isrecordlocked">
      <applyformatting>F</applyformatting>
      <defaultchecked>F</defaultchecked>
      <defaultselection></defaultselection>
      <defaultvalue></defaultvalue>
      <description></description>
      <displaytype>NORMAL</displaytype>
      <dynamicdefault></dynamicdefault>
      <fieldtype>CHECKBOX</fieldtype>
      <help></help>
      <label>Record Locked</label>
      <linktext></linktext>
      <maxvalue></maxvalue>
      <minvalue></minvalue>
      <selectrecordtype></selectrecordtype>
      <storevalue>T</storevalue>
    </workflowcustomfield>
  </workflowcustomfields>
  <workflowstates>
    <workflowstate scriptid="workflowstate27">
      <description></description>
      <donotexitworkflow>F</donotexitworkflow>
      <name>Initiation</name>
      <positionx>233</positionx>
      <positiony>133</positiony>
      <workflowactions triggertype="ONENTRY">
        <setfieldvalueaction scriptid="workflowaction104">
          <clienttriggerfields></clienttriggerfields>
          <conditionsavedsearch></conditionsavedsearch>
          <contexttypes>ACTION|BANKCONNECTIVITY|BANKSTATEMENTPARSER|BUNDLEINSTALLATION|CLIENT|CSVIMPORT|CUSTOMGLLINES|CUSTOMMASSUPDATE|RECORDACTION|DATASETBUILDER|DEBUGGER|EMAILCAPTURE|FICONNECTIVITY|FIPARSER|MAPREDUCE|OFFLINECLIENT|OTHER|PAYMENTPOSTBACK|PAYMENTGATEWAY|PLATFORMEXTENSION|PORTLET|PROMOTIONS|CONSOLRATEADJUSTOR|RESTWEBSERVICES|RESTLET|ADVANCEDREVREC|SCHEDULED|SDFINSTALLATION|SHIPPINGPARTNERS|WEBSERVICES|SUITELET|TAXCALCULATION|USEREVENT|USERINTERFACE|WORKBOOKBUILDER|WORKFLOW</contexttypes>
          <eventtypes></eventtypes>
          <field>STDENTITYISINACTIVE</field>
          <isinactive>F</isinactive>
          <scheduledelay></scheduledelay>
          <schedulemode>DELAY</schedulemode>
          <schedulerecurrence></schedulerecurrence>
          <scheduletimeofday></scheduletimeofday>
          <scheduletimeunit></scheduletimeunit>
          <valuechecked>T</valuechecked>
          <valuedate></valuedate>
          <valuefield></valuefield>
          <valueformula></valueformula>
          <valuejoinfield></valuejoinfield>
          <valueselect></valueselect>
          <valuetext></valuetext>
          <valuetype>STATIC</valuetype>
          <initcondition>
            <formula></formula>
            <type>VISUAL_BUILDER</type>
          </initcondition>
        </setfieldvalueaction>
        <setfieldvalueaction scriptid="workflowaction105">
          <clienttriggerfields></clienttriggerfields>
          <conditionsavedsearch></conditionsavedsearch>
          <contexttypes>ACTION|BANKCONNECTIVITY|BANKSTATEMENTPARSER|BUNDLEINSTALLATION|CLIENT|CSVIMPORT|CUSTOMGLLINES|CUSTOMMASSUPDATE|RECORDACTION|DATASETBUILDER|DEBUGGER|EMAILCAPTURE|FICONNECTIVITY|FIPARSER|MAPREDUCE|OFFLINECLIENT|OTHER|PAYMENTPOSTBACK|PAYMENTGATEWAY|PLATFORMEXTENSION|PORTLET|PROMOTIONS|CONSOLRATEADJUSTOR|RESTWEBSERVICES|RESTLET|ADVANCEDREVREC|SCHEDULED|SDFINSTALLATION|SHIPPINGPARTNERS|WEBSERVICES|SUITELET|TAXCALCULATION|USEREVENT|USERINTERFACE|WORKBOOKBUILDER|WORKFLOW</contexttypes>
          <eventtypes></eventtypes>
          <field>[scriptid=customworkflow_kd_new_vendor_approval.custworkflow_kd_created_by]</field>
          <isinactive>F</isinactive>
          <scheduledelay></scheduledelay>
          <schedulemode>DELAY</schedulemode>
          <schedulerecurrence></schedulerecurrence>
          <scheduletimeofday></scheduletimeofday>
          <scheduletimeunit></scheduletimeunit>
          <valuechecked>F</valuechecked>
          <valuedate></valuedate>
          <valuefield>STDUSERUSER</valuefield>
          <valueformula></valueformula>
          <valuejoinfield></valuejoinfield>
          <valueselect></valueselect>
          <valuetext></valuetext>
          <valuetype>FIELD</valuetype>
          <initcondition>
            <formula></formula>
            <type>VISUAL_BUILDER</type>
          </initcondition>
        </setfieldvalueaction>
        <setfieldvalueaction scriptid="workflowaction131">
          <clienttriggerfields></clienttriggerfields>
          <conditionsavedsearch></conditionsavedsearch>
          <contexttypes>ACTION|BANKCONNECTIVITY|BANKSTATEMENTPARSER|BUNDLEINSTALLATION|CLIENT|CSVIMPORT|CUSTOMGLLINES|CUSTOMMASSUPDATE|RECORDACTION|DATASETBUILDER|DEBUGGER|EMAILCAPTURE|FICONNECTIVITY|FIPARSER|MAPREDUCE|OFFLINECLIENT|OTHER|PAYMENTPOSTBACK|PAYMENTGATEWAY|PLATFORMEXTENSION|PORTLET|PROMOTIONS|CONSOLRATEADJUSTOR|RESTWEBSERVICES|RESTLET|ADVANCEDREVREC|SCHEDULED|SDFINSTALLATION|SHIPPINGPARTNERS|WEBSERVICES|SUITELET|TAXCALCULATION|USEREVENT|USERINTERFACE|WORKBOOKBUILDER|WORKFLOW</contexttypes>
          <eventtypes></eventtypes>
          <field>[scriptid=custentity_kd_approved_by]</field>
          <isinactive>F</isinactive>
          <scheduledelay></scheduledelay>
          <schedulemode>DELAY</schedulemode>
          <schedulerecurrence></schedulerecurrence>
          <scheduletimeofday></scheduletimeofday>
          <scheduletimeunit></scheduletimeunit>
          <valuechecked>F</valuechecked>
          <valuedate></valuedate>
          <valuefield></valuefield>
          <valueformula></valueformula>
          <valuejoinfield></valuejoinfield>
          <valueselect></valueselect>
          <valuetext></valuetext>
          <valuetype>STATIC</valuetype>
          <initcondition>
            <formula></formula>
            <type>VISUAL_BUILDER</type>
          </initcondition>
        </setfieldvalueaction>
      </workflowactions>
      <workflowtransitions>
        <workflowtransition scriptid="workflowtransition233">
          <buttonaction></buttonaction>
          <conditionsavedsearch></conditionsavedsearch>
          <contexttypes>ACTION|BANKCONNECTIVITY|BANKSTATEMENTPARSER|BUNDLEINSTALLATION|CLIENT|CSVIMPORT|CUSTOMGLLINES|CUSTOMMASSUPDATE|RECORDACTION|DATASETBUILDER|DEBUGGER|EMAILCAPTURE|FICONNECTIVITY|FIPARSER|MAPREDUCE|OFFLINECLIENT|OTHER|PAYMENTPOSTBACK|PAYMENTGATEWAY|PLATFORMEXTENSION|PORTLET|PROMOTIONS|CONSOLRATEADJUSTOR|RESTWEBSERVICES|RESTLET|ADVANCEDREVREC|SCHEDULED|SDFINSTALLATION|SHIPPINGPARTNERS|WEBSERVICES|SUITELET|TAXCALCULATION|USEREVENT|USERINTERFACE|WORKBOOKBUILDER|WORKFLOW</contexttypes>
          <eventtypes></eventtypes>
          <scheduledelay></scheduledelay>
          <scheduletimeunit></scheduletimeunit>
          <tostate>[scriptid=customworkflow_kd_new_vendor_approval.workflowstate28]</tostate>
          <triggertype>BEFORESUBMIT</triggertype>
          <waitforworkflow></waitforworkflow>
          <waitforworkflowstate></waitforworkflowstate>
          <initcondition>
            <formula><![CDATA["Terms" IN ("Term1","Term2","Term3") OR isEmpty("Terms") = 'T']]></formula>
            <type>VISUAL_BUILDER</type>
            <parameters>
              <parameter>
                <name>Terms</name>
                <value>STDENTITYTERMS</value>
              </parameter>
              <parameter>
                <name>Term1</name>
                <selectrecordtype>-199</selectrecordtype>
                <value>[ACCOUNT_SPECIFIC_VALUE]</value>
              </parameter>
              <parameter>
                <name>Term2</name>
                <selectrecordtype>-199</selectrecordtype>
                <value>[ACCOUNT_SPECIFIC_VALUE]</value>
              </parameter>
              <parameter>
                <name>Term3</name>
                <selectrecordtype>-199</selectrecordtype>
                <value>[ACCOUNT_SPECIFIC_VALUE]</value>
              </parameter>
            </parameters>
          </initcondition>
        </workflowtransition>
        <workflowtransition scriptid="workflowtransition234">
          <buttonaction></buttonaction>
          <conditionsavedsearch></conditionsavedsearch>
          <contexttypes>ACTION|BANKCONNECTIVITY|BANKSTATEMENTPARSER|BUNDLEINSTALLATION|CLIENT|CSVIMPORT|CUSTOMGLLINES|CUSTOMMASSUPDATE|RECORDACTION|DATASETBUILDER|DEBUGGER|EMAILCAPTURE|FICONNECTIVITY|FIPARSER|MAPREDUCE|OFFLINECLIENT|OTHER|PAYMENTPOSTBACK|PAYMENTGATEWAY|PLATFORMEXTENSION|PORTLET|PROMOTIONS|CONSOLRATEADJUSTOR|RESTWEBSERVICES|RESTLET|ADVANCEDREVREC|SCHEDULED|SDFINSTALLATION|SHIPPINGPARTNERS|WEBSERVICES|SUITELET|TAXCALCULATION|USEREVENT|USERINTERFACE|WORKBOOKBUILDER|WORKFLOW</contexttypes>
          <eventtypes></eventtypes>
          <scheduledelay></scheduledelay>
          <scheduletimeunit></scheduletimeunit>
          <tostate>[scriptid=customworkflow_kd_new_vendor_approval.workflowstate29]</tostate>
          <triggertype>BEFORESUBMIT</triggertype>
          <waitforworkflow></waitforworkflow>
          <waitforworkflowstate></waitforworkflowstate>
          <initcondition>
            <formula><![CDATA["Terms" NOT IN ("Term1","Term2","Term3") AND isEmpty("Terms") = 'F']]></formula>
            <type>VISUAL_BUILDER</type>
            <parameters>
              <parameter>
                <name>Terms</name>
                <value>STDENTITYTERMS</value>
              </parameter>
              <parameter>
                <name>Term1</name>
                <selectrecordtype>-199</selectrecordtype>
                <value>[ACCOUNT_SPECIFIC_VALUE]</value>
              </parameter>
              <parameter>
                <name>Term2</name>
                <selectrecordtype>-199</selectrecordtype>
                <value>[ACCOUNT_SPECIFIC_VALUE]</value>
              </parameter>
              <parameter>
                <name>Term3</name>
                <selectrecordtype>-199</selectrecordtype>
                <value>[ACCOUNT_SPECIFIC_VALUE]</value>
              </parameter>
            </parameters>
          </initcondition>
        </workflowtransition>
      </workflowtransitions>
    </workflowstate>
    <workflowstate scriptid="workflowstate28">
      <description>Newly created Vendor will undergo approval when Terms selected is either Due on Receipt, Net 15, Prepaid or empty/null.&#xd;
&#xd;
Approvers are employees that is either a Finance Management or Ops Lead.</description>
      <donotexitworkflow>F</donotexitworkflow>
      <name>Pending Approval</name>
      <positionx>393</positionx>
      <positiony>243</positiony>
      <workflowactions triggertype="BEFORELOAD">
        <lockrecordaction scriptid="workflowaction106">
          <conditionsavedsearch></conditionsavedsearch>
          <contexttypes>ACTION|BANKCONNECTIVITY|BANKSTATEMENTPARSER|BUNDLEINSTALLATION|CLIENT|CSVIMPORT|CUSTOMGLLINES|CUSTOMMASSUPDATE|RECORDACTION|DATASETBUILDER|DEBUGGER|EMAILCAPTURE|FICONNECTIVITY|FIPARSER|MAPREDUCE|OFFLINECLIENT|OTHER|PAYMENTPOSTBACK|PAYMENTGATEWAY|PLATFORMEXTENSION|PORTLET|PROMOTIONS|CONSOLRATEADJUSTOR|RESTWEBSERVICES|RESTLET|ADVANCEDREVREC|SCHEDULED|SDFINSTALLATION|SHIPPINGPARTNERS|WEBSERVICES|SUITELET|TAXCALCULATION|USEREVENT|USERINTERFACE|WORKBOOKBUILDER|WORKFLOW</contexttypes>
          <eventtypes></eventtypes>
          <isinactive>F</isinactive>
          <initcondition>
            <formula></formula>
            <type>VISUAL_BUILDER</type>
          </initcondition>
        </lockrecordaction>
        <addbuttonaction scriptid="workflowactionapprove">
          <checkconditionbeforeexecution>T</checkconditionbeforeexecution>
          <conditionsavedsearch></conditionsavedsearch>
          <contexttypes>ACTION|BANKCONNECTIVITY|BANKSTATEMENTPARSER|BUNDLEINSTALLATION|CLIENT|CSVIMPORT|CUSTOMGLLINES|CUSTOMMASSUPDATE|RECORDACTION|DATASETBUILDER|DEBUGGER|EMAILCAPTURE|FICONNECTIVITY|FIPARSER|MAPREDUCE|OFFLINECLIENT|OTHER|PAYMENTPOSTBACK|PAYMENTGATEWAY|PLATFORMEXTENSION|PORTLET|PROMOTIONS|CONSOLRATEADJUSTOR|RESTWEBSERVICES|RESTLET|ADVANCEDREVREC|SCHEDULED|SDFINSTALLATION|SHIPPINGPARTNERS|WEBSERVICES|SUITELET|TAXCALCULATION|USEREVENT|USERINTERFACE|WORKBOOKBUILDER|WORKFLOW</contexttypes>
          <eventtypes></eventtypes>
          <isinactive>F</isinactive>
          <label>Approve</label>
          <saverecordfirst>T</saverecordfirst>
          <initcondition>
            <formula><![CDATA[( "User" NOT IN ("Workflow:Created By (4)") OR "User Role" IN ("Role1") ) AND ( isChecked("User:Finance Management") = 'T' OR isChecked("User:Ops Lead Management") = 'T' )]]></formula>
            <type>VISUAL_BUILDER</type>
            <parameters>
              <parameter>
                <name>User</name>
                <value>STDUSERUSER</value>
              </parameter>
              <parameter>
                <name>Workflow:Created By (4)</name>
                <value>[scriptid=customworkflow_kd_new_vendor_approval.custworkflow_kd_created_by]</value>
              </parameter>
              <parameter>
                <name>User Role</name>
                <value>STDUSERROLE</value>
              </parameter>
              <parameter>
                <name>Role1</name>
                <selectrecordtype>-118</selectrecordtype>
                <value>ADMINISTRATOR</value>
              </parameter>
              <parameter>
                <name>User:Finance Management</name>
                <value>STDUSERUSER:[scriptid=custentity_kd_isfinancemgmt]</value>
              </parameter>
              <parameter>
                <name>User:Ops Lead Management</name>
                <value>STDUSERUSER:[scriptid=custentity_kd_isopsleadmgmt]</value>
              </parameter>
            </parameters>
          </initcondition>
        </addbuttonaction>
        <addbuttonaction scriptid="workflowactiondrop">
          <checkconditionbeforeexecution>T</checkconditionbeforeexecution>
          <conditionsavedsearch></conditionsavedsearch>
          <contexttypes>ACTION|BANKCONNECTIVITY|BANKSTATEMENTPARSER|BUNDLEINSTALLATION|CLIENT|CSVIMPORT|CUSTOMGLLINES|CUSTOMMASSUPDATE|RECORDACTION|DATASETBUILDER|DEBUGGER|EMAILCAPTURE|FICONNECTIVITY|FIPARSER|MAPREDUCE|OFFLINECLIENT|OTHER|PAYMENTPOSTBACK|PAYMENTGATEWAY|PLATFORMEXTENSION|PORTLET|PROMOTIONS|CONSOLRATEADJUSTOR|RESTWEBSERVICES|RESTLET|ADVANCEDREVREC|SCHEDULED|SDFINSTALLATION|SHIPPINGPARTNERS|WEBSERVICES|SUITELET|TAXCALCULATION|USEREVENT|USERINTERFACE|WORKBOOKBUILDER|WORKFLOW</contexttypes>
          <eventtypes></eventtypes>
          <isinactive>F</isinactive>
          <label>Drop</label>
          <saverecordfirst>T</saverecordfirst>
          <initcondition>
            <formula><![CDATA[( "User" NOT IN ("Workflow:Created By (4)") OR "User Role" IN ("Role1") ) AND ( isChecked("User:Finance Management") = 'T' OR isChecked("User:Ops Lead Management") = 'T' )]]></formula>
            <type>VISUAL_BUILDER</type>
            <parameters>
              <parameter>
                <name>User</name>
                <value>STDUSERUSER</value>
              </parameter>
              <parameter>
                <name>Workflow:Created By (4)</name>
                <value>[scriptid=customworkflow_kd_new_vendor_approval.custworkflow_kd_created_by]</value>
              </parameter>
              <parameter>
                <name>User Role</name>
                <value>STDUSERROLE</value>
              </parameter>
              <parameter>
                <name>Role1</name>
                <selectrecordtype>-118</selectrecordtype>
                <value>ADMINISTRATOR</value>
              </parameter>
              <parameter>
                <name>User:Finance Management</name>
                <value>STDUSERUSER:[scriptid=custentity_kd_isfinancemgmt]</value>
              </parameter>
              <parameter>
                <name>User:Ops Lead Management</name>
                <value>STDUSERUSER:[scriptid=custentity_kd_isopsleadmgmt]</value>
              </parameter>
            </parameters>
          </initcondition>
        </addbuttonaction>
      </workflowactions>
      <workflowactions triggertype="BEFORESUBMIT">
        <returnusererroraction scriptid="workflowaction_kd_record_is_locked">
          <clienttriggerfields></clienttriggerfields>
          <conditionsavedsearch></conditionsavedsearch>
          <contexttypes>ACTION|BANKCONNECTIVITY|BANKSTATEMENTPARSER|BUNDLEINSTALLATION|CLIENT|CSVIMPORT|CUSTOMGLLINES|CUSTOMMASSUPDATE|RECORDACTION|DATASETBUILDER|DEBUGGER|EMAILCAPTURE|FICONNECTIVITY|FIPARSER|MAPREDUCE|OFFLINECLIENT|OTHER|PAYMENTPOSTBACK|PAYMENTGATEWAY|PLATFORMEXTENSION|PORTLET|PROMOTIONS|CONSOLRATEADJUSTOR|RESTWEBSERVICES|RESTLET|ADVANCEDREVREC|SCHEDULED|SDFINSTALLATION|SHIPPINGPARTNERS|WEBSERVICES|SUITELET|TAXCALCULATION|USEREVENT|USERINTERFACE|WORKBOOKBUILDER|WORKFLOW</contexttypes>
          <errortext>Vendor is pending approval and cannot be edited.</errortext>
          <eventtypes></eventtypes>
          <isinactive>F</isinactive>
          <initcondition>
            <formula><![CDATA[isChecked("Workflow:Record Locked") = 'T']]></formula>
            <type>VISUAL_BUILDER</type>
            <parameters>
              <parameter>
                <name>Workflow:Record Locked</name>
                <value>[scriptid=customworkflow_kd_new_vendor_approval.custworkflow_kd_isrecordlocked]</value>
              </parameter>
            </parameters>
          </initcondition>
        </returnusererroraction>
      </workflowactions>
      <workflowactions triggertype="AFTERSUBMIT">
        <setfieldvalueaction scriptid="workflowaction107">
          <clienttriggerfields></clienttriggerfields>
          <conditionsavedsearch></conditionsavedsearch>
          <contexttypes>ACTION|BANKCONNECTIVITY|BANKSTATEMENTPARSER|BUNDLEINSTALLATION|CLIENT|CSVIMPORT|CUSTOMGLLINES|CUSTOMMASSUPDATE|RECORDACTION|DATASETBUILDER|DEBUGGER|EMAILCAPTURE|FICONNECTIVITY|FIPARSER|MAPREDUCE|OFFLINECLIENT|OTHER|PAYMENTPOSTBACK|PAYMENTGATEWAY|PLATFORMEXTENSION|PORTLET|PROMOTIONS|CONSOLRATEADJUSTOR|RESTWEBSERVICES|RESTLET|ADVANCEDREVREC|SCHEDULED|SDFINSTALLATION|SHIPPINGPARTNERS|WEBSERVICES|SUITELET|TAXCALCULATION|USEREVENT|USERINTERFACE|WORKBOOKBUILDER|WORKFLOW</contexttypes>
          <eventtypes></eventtypes>
          <field>[scriptid=customworkflow_kd_new_vendor_approval.custworkflow_kd_isrecordlocked]</field>
          <isinactive>F</isinactive>
          <scheduledelay></scheduledelay>
          <schedulemode>DELAY</schedulemode>
          <schedulerecurrence></schedulerecurrence>
          <scheduletimeofday></scheduletimeofday>
          <scheduletimeunit></scheduletimeunit>
          <valuechecked>T</valuechecked>
          <valuedate></valuedate>
          <valuefield></valuefield>
          <valueformula></valueformula>
          <valuejoinfield></valuejoinfield>
          <valueselect></valueselect>
          <valuetext></valuetext>
          <valuetype>STATIC</valuetype>
          <initcondition>
            <formula></formula>
            <type>VISUAL_BUILDER</type>
          </initcondition>
        </setfieldvalueaction>
        <customaction scriptid="workflowaction110">
          <conditionsavedsearch></conditionsavedsearch>
          <contexttypes>ACTION|BANKCONNECTIVITY|BANKSTATEMENTPARSER|BUNDLEINSTALLATION|CLIENT|CSVIMPORT|CUSTOMGLLINES|CUSTOMMASSUPDATE|RECORDACTION|DATASETBUILDER|DEBUGGER|EMAILCAPTURE|FICONNECTIVITY|FIPARSER|MAPREDUCE|OFFLINECLIENT|OTHER|PAYMENTPOSTBACK|PAYMENTGATEWAY|PLATFORMEXTENSION|PORTLET|PROMOTIONS|CONSOLRATEADJUSTOR|RESTWEBSERVICES|RESTLET|ADVANCEDREVREC|SCHEDULED|SDFINSTALLATION|SHIPPINGPARTNERS|WEBSERVICES|SUITELET|TAXCALCULATION|USEREVENT|USERINTERFACE|WORKBOOKBUILDER|WORKFLOW</contexttypes>
          <eventtypes></eventtypes>
          <isinactive>F</isinactive>
          <resultfield></resultfield>
          <scheduledelay></scheduledelay>
          <schedulemode>DELAY</schedulemode>
          <schedulerecurrence></schedulerecurrence>
          <scheduletimeofday></scheduletimeofday>
          <scheduletimeunit></scheduletimeunit>
          <scripttype>[scriptid=customscript_kd_wa_email_approval]</scripttype>
          <initcondition>
            <formula></formula>
            <type>VISUAL_BUILDER</type>
          </initcondition>
          <parametersettings>
            <parametersetting>
              <targetparameter>[scriptid=customscript_kd_wa_email_approval.custscript_kd_wa_email_approval_type]</targetparameter>
              <valuechecked></valuechecked>
              <valuedate></valuedate>
              <valuefield></valuefield>
              <valueformula></valueformula>
              <valuejoinfield></valuejoinfield>
              <valueselect></valueselect>
              <valuetext></valuetext>
            </parametersetting>
            <parametersetting>
              <targetparameter>[scriptid=customscript_kd_wa_email_approval.custscript_kd_wa_cfo_apprvl_required]</targetparameter>
              <valuechecked></valuechecked>
              <valuedate></valuedate>
              <valuefield></valuefield>
              <valueformula></valueformula>
              <valuejoinfield></valuejoinfield>
              <valueselect></valueselect>
              <valuetext></valuetext>
            </parametersetting>
          </parametersettings>
        </customaction>
      </workflowactions>
      <workflowtransitions>
        <workflowtransition scriptid="workflowtransition235">
          <buttonaction>[scriptid=customworkflow_kd_new_vendor_approval.workflowstate28.workflowactionapprove]</buttonaction>
          <conditionsavedsearch></conditionsavedsearch>
          <contexttypes>ACTION|BANKCONNECTIVITY|BANKSTATEMENTPARSER|BUNDLEINSTALLATION|CLIENT|CSVIMPORT|CUSTOMGLLINES|CUSTOMMASSUPDATE|RECORDACTION|DATASETBUILDER|DEBUGGER|EMAILCAPTURE|FICONNECTIVITY|FIPARSER|MAPREDUCE|OFFLINECLIENT|OTHER|PAYMENTPOSTBACK|PAYMENTGATEWAY|PLATFORMEXTENSION|PORTLET|PROMOTIONS|CONSOLRATEADJUSTOR|RESTWEBSERVICES|RESTLET|ADVANCEDREVREC|SCHEDULED|SDFINSTALLATION|SHIPPINGPARTNERS|WEBSERVICES|SUITELET|TAXCALCULATION|USEREVENT|USERINTERFACE|WORKBOOKBUILDER|WORKFLOW</contexttypes>
          <eventtypes></eventtypes>
          <scheduledelay></scheduledelay>
          <scheduletimeunit></scheduletimeunit>
          <tostate>[scriptid=customworkflow_kd_new_vendor_approval.workflowstate29]</tostate>
          <triggertype></triggertype>
          <waitforworkflow></waitforworkflow>
          <waitforworkflowstate></waitforworkflowstate>
          <initcondition>
            <formula></formula>
            <type>VISUAL_BUILDER</type>
          </initcondition>
        </workflowtransition>
        <workflowtransition scriptid="workflowtransition236">
          <buttonaction>[scriptid=customworkflow_kd_new_vendor_approval.workflowstate28.workflowactiondrop]</buttonaction>
          <conditionsavedsearch></conditionsavedsearch>
          <contexttypes>ACTION|BANKCONNECTIVITY|BANKSTATEMENTPARSER|BUNDLEINSTALLATION|CLIENT|CSVIMPORT|CUSTOMGLLINES|CUSTOMMASSUPDATE|RECORDACTION|DATASETBUILDER|DEBUGGER|EMAILCAPTURE|FICONNECTIVITY|FIPARSER|MAPREDUCE|OFFLINECLIENT|OTHER|PAYMENTPOSTBACK|PAYMENTGATEWAY|PLATFORMEXTENSION|PORTLET|PROMOTIONS|CONSOLRATEADJUSTOR|RESTWEBSERVICES|RESTLET|ADVANCEDREVREC|SCHEDULED|SDFINSTALLATION|SHIPPINGPARTNERS|WEBSERVICES|SUITELET|TAXCALCULATION|USEREVENT|USERINTERFACE|WORKBOOKBUILDER|WORKFLOW</contexttypes>
          <eventtypes></eventtypes>
          <scheduledelay></scheduledelay>
          <scheduletimeunit></scheduletimeunit>
          <tostate>[scriptid=customworkflow_kd_new_vendor_approval.workflowstate30]</tostate>
          <triggertype></triggertype>
          <waitforworkflow></waitforworkflow>
          <waitforworkflowstate></waitforworkflowstate>
          <initcondition>
            <formula></formula>
            <type>VISUAL_BUILDER</type>
          </initcondition>
        </workflowtransition>
      </workflowtransitions>
    </workflowstate>
    <workflowstate scriptid="workflowstate29">
      <description></description>
      <donotexitworkflow>F</donotexitworkflow>
      <name>Approved</name>
      <positionx>233</positionx>
      <positiony>373</positiony>
      <workflowactions triggertype="ONENTRY">
        <setfieldvalueaction scriptid="workflowaction108">
          <clienttriggerfields></clienttriggerfields>
          <conditionsavedsearch></conditionsavedsearch>
          <contexttypes>ACTION|BANKCONNECTIVITY|BANKSTATEMENTPARSER|BUNDLEINSTALLATION|CLIENT|CSVIMPORT|CUSTOMGLLINES|CUSTOMMASSUPDATE|RECORDACTION|DATASETBUILDER|DEBUGGER|EMAILCAPTURE|FICONNECTIVITY|FIPARSER|MAPREDUCE|OFFLINECLIENT|OTHER|PAYMENTPOSTBACK|PAYMENTGATEWAY|PLATFORMEXTENSION|PORTLET|PROMOTIONS|CONSOLRATEADJUSTOR|RESTWEBSERVICES|RESTLET|ADVANCEDREVREC|SCHEDULED|SDFINSTALLATION|SHIPPINGPARTNERS|WEBSERVICES|SUITELET|TAXCALCULATION|USEREVENT|USERINTERFACE|WORKBOOKBUILDER|WORKFLOW</contexttypes>
          <eventtypes></eventtypes>
          <field>STDENTITYISINACTIVE</field>
          <isinactive>F</isinactive>
          <scheduledelay></scheduledelay>
          <schedulemode>DELAY</schedulemode>
          <schedulerecurrence></schedulerecurrence>
          <scheduletimeofday></scheduletimeofday>
          <scheduletimeunit></scheduletimeunit>
          <valuechecked>F</valuechecked>
          <valuedate></valuedate>
          <valuefield></valuefield>
          <valueformula></valueformula>
          <valuejoinfield></valuejoinfield>
          <valueselect></valueselect>
          <valuetext></valuetext>
          <valuetype>STATIC</valuetype>
          <initcondition>
            <formula></formula>
            <type>VISUAL_BUILDER</type>
          </initcondition>
        </setfieldvalueaction>
        <setfieldvalueaction scriptid="workflowaction109">
          <clienttriggerfields></clienttriggerfields>
          <conditionsavedsearch></conditionsavedsearch>
          <contexttypes>ACTION|BANKCONNECTIVITY|BANKSTATEMENTPARSER|BUNDLEINSTALLATION|CLIENT|CSVIMPORT|CUSTOMGLLINES|CUSTOMMASSUPDATE|RECORDACTION|DATASETBUILDER|DEBUGGER|EMAILCAPTURE|FICONNECTIVITY|FIPARSER|MAPREDUCE|OFFLINECLIENT|OTHER|PAYMENTPOSTBACK|PAYMENTGATEWAY|PLATFORMEXTENSION|PORTLET|PROMOTIONS|CONSOLRATEADJUSTOR|RESTWEBSERVICES|RESTLET|ADVANCEDREVREC|SCHEDULED|SDFINSTALLATION|SHIPPINGPARTNERS|WEBSERVICES|SUITELET|TAXCALCULATION|USEREVENT|USERINTERFACE|WORKBOOKBUILDER|WORKFLOW</contexttypes>
          <eventtypes></eventtypes>
          <field>[scriptid=customworkflow_kd_new_vendor_approval.custworkflow_kd_isrecordlocked]</field>
          <isinactive>F</isinactive>
          <scheduledelay></scheduledelay>
          <schedulemode>DELAY</schedulemode>
          <schedulerecurrence></schedulerecurrence>
          <scheduletimeofday></scheduletimeofday>
          <scheduletimeunit></scheduletimeunit>
          <valuechecked>F</valuechecked>
          <valuedate></valuedate>
          <valuefield></valuefield>
          <valueformula></valueformula>
          <valuejoinfield></valuejoinfield>
          <valueselect></valueselect>
          <valuetext></valuetext>
          <valuetype>STATIC</valuetype>
          <initcondition>
            <formula></formula>
            <type>VISUAL_BUILDER</type>
          </initcondition>
        </setfieldvalueaction>
        <setfieldvalueaction scriptid="workflowaction111">
          <clienttriggerfields></clienttriggerfields>
          <conditionsavedsearch></conditionsavedsearch>
          <contexttypes>ACTION|BANKCONNECTIVITY|BANKSTATEMENTPARSER|BUNDLEINSTALLATION|CLIENT|CSVIMPORT|CUSTOMGLLINES|CUSTOMMASSUPDATE|RECORDACTION|DATASETBUILDER|DEBUGGER|EMAILCAPTURE|FICONNECTIVITY|FIPARSER|MAPREDUCE|OFFLINECLIENT|OTHER|PAYMENTPOSTBACK|PAYMENTGATEWAY|PLATFORMEXTENSION|PORTLET|PROMOTIONS|CONSOLRATEADJUSTOR|RESTWEBSERVICES|RESTLET|ADVANCEDREVREC|SCHEDULED|SDFINSTALLATION|SHIPPINGPARTNERS|WEBSERVICES|SUITELET|TAXCALCULATION|USEREVENT|USERINTERFACE|WORKBOOKBUILDER|WORKFLOW</contexttypes>
          <eventtypes></eventtypes>
          <field>[scriptid=custentity_kd_approved_by]</field>
          <isinactive>F</isinactive>
          <scheduledelay></scheduledelay>
          <schedulemode>DELAY</schedulemode>
          <schedulerecurrence></schedulerecurrence>
          <scheduletimeofday></scheduletimeofday>
          <scheduletimeunit></scheduletimeunit>
          <valuechecked>F</valuechecked>
          <valuedate></valuedate>
          <valuefield>STDUSERUSER</valuefield>
          <valueformula></valueformula>
          <valuejoinfield></valuejoinfield>
          <valueselect></valueselect>
          <valuetext></valuetext>
          <valuetype>FIELD</valuetype>
          <initcondition>
            <formula></formula>
            <type>VISUAL_BUILDER</type>
          </initcondition>
        </setfieldvalueaction>
      </workflowactions>
      <workflowtransitions>
        <workflowtransition scriptid="workflowtransition242">
          <buttonaction></buttonaction>
          <conditionsavedsearch></conditionsavedsearch>
          <contexttypes>ACTION|BANKCONNECTIVITY|BANKSTATEMENTPARSER|BUNDLEINSTALLATION|CLIENT|CSVIMPORT|CUSTOMGLLINES|CUSTOMMASSUPDATE|RECORDACTION|DATASETBUILDER|DEBUGGER|EMAILCAPTURE|FICONNECTIVITY|FIPARSER|MAPREDUCE|OFFLINECLIENT|OTHER|PAYMENTPOSTBACK|PAYMENTGATEWAY|PLATFORMEXTENSION|PORTLET|PROMOTIONS|CONSOLRATEADJUSTOR|RESTWEBSERVICES|RESTLET|ADVANCEDREVREC|SCHEDULED|SDFINSTALLATION|SHIPPINGPARTNERS|WEBSERVICES|SUITELET|TAXCALCULATION|USEREVENT|USERINTERFACE|WORKBOOKBUILDER|WORKFLOW</contexttypes>
          <eventtypes></eventtypes>
          <scheduledelay></scheduledelay>
          <scheduletimeunit></scheduletimeunit>
          <tostate>[scriptid=customworkflow_kd_new_vendor_approval.workflowstate27]</tostate>
          <triggertype></triggertype>
          <waitforworkflow></waitforworkflow>
          <waitforworkflowstate></waitforworkflowstate>
          <initcondition>
            <formula><![CDATA[( "Terms" IN ("Term1","Term2","Term3") OR isEmpty("Terms") = 'T' ) AND "Old Record:Terms" NOT IN ("Terms")]]></formula>
            <type>VISUAL_BUILDER</type>
            <parameters>
              <parameter>
                <name>Terms</name>
                <value>STDENTITYTERMS</value>
              </parameter>
              <parameter>
                <name>Term1</name>
                <selectrecordtype>-199</selectrecordtype>
                <value>[ACCOUNT_SPECIFIC_VALUE]</value>
              </parameter>
              <parameter>
                <name>Term2</name>
                <selectrecordtype>-199</selectrecordtype>
                <value>[ACCOUNT_SPECIFIC_VALUE]</value>
              </parameter>
              <parameter>
                <name>Term3</name>
                <selectrecordtype>-199</selectrecordtype>
                <value>[ACCOUNT_SPECIFIC_VALUE]</value>
              </parameter>
              <parameter>
                <name>Old Record:Terms</name>
                <value>@OLDRECORD@:STDENTITYTERMS</value>
              </parameter>
            </parameters>
          </initcondition>
        </workflowtransition>
      </workflowtransitions>
    </workflowstate>
    <workflowstate scriptid="workflowstate30">
      <description></description>
      <donotexitworkflow>T</donotexitworkflow>
      <name>Dropped</name>
      <positionx>613</positionx>
      <positiony>243</positiony>
      <workflowactions triggertype="BEFORELOAD">
        <lockrecordaction scriptid="workflowaction112">
          <conditionsavedsearch></conditionsavedsearch>
          <contexttypes>ACTION|BANKCONNECTIVITY|BANKSTATEMENTPARSER|BUNDLEINSTALLATION|CLIENT|CSVIMPORT|CUSTOMGLLINES|CUSTOMMASSUPDATE|RECORDACTION|DATASETBUILDER|DEBUGGER|EMAILCAPTURE|FICONNECTIVITY|FIPARSER|MAPREDUCE|OFFLINECLIENT|OTHER|PAYMENTPOSTBACK|PAYMENTGATEWAY|PLATFORMEXTENSION|PORTLET|PROMOTIONS|CONSOLRATEADJUSTOR|RESTWEBSERVICES|RESTLET|ADVANCEDREVREC|SCHEDULED|SDFINSTALLATION|SHIPPINGPARTNERS|WEBSERVICES|SUITELET|TAXCALCULATION|USEREVENT|USERINTERFACE|WORKBOOKBUILDER|WORKFLOW</contexttypes>
          <eventtypes></eventtypes>
          <isinactive>F</isinactive>
          <initcondition>
            <formula></formula>
            <type>VISUAL_BUILDER</type>
          </initcondition>
        </lockrecordaction>
      </workflowactions>
    </workflowstate>
  </workflowstates>
</workflow>